pipenvExample/__init__.py
pipenvExample/main.py
pipenvExample-0.1.1.dist-info/METADATA
pipenvExample-0.1.1.dist-info/WHEEL
pipenvExample-0.1.1.dist-info/top_level.txt
pipenvExample-0.1.1.dist-info/RECORD
