Metadata-Version: 2.1
Name: pipenvExample
Version: 0.1.1
Summary: Example pipenv project
Home-page: UNKNOWN
Author: Alan Bacon
Author-email: alan@bacontowers.co.uk
License: UNKNOWN
Platform: UNKNOWN
Requires-Dist: fnf (<2.0.0)
